gearhorn
